LICENSE.txt
MANIFEST.in
README.txt
setup.py
pcart_product_finder/__init__.py
pcart_product_finder/admin.py
pcart_product_finder/apps.py
pcart_product_finder/cms_plugins.py
pcart_product_finder/forms.py
pcart_product_finder/models.py
pcart_product_finder/triggers.py
pcart_product_finder/urls.py
pcart_product_finder/views.py
pcart_product_finder.egg-info/PKG-INFO
pcart_product_finder.egg-info/SOURCES.txt
pcart_product_finder.egg-info/dependency_links.txt
pcart_product_finder.egg-info/not-zip-safe
pcart_product_finder.egg-info/requires.txt
pcart_product_finder.egg-info/top_level.txt
pcart_product_finder/fixtures/cars-tires-disks.json
pcart_product_finder/locale/ru/LC_MESSAGES/django.mo
pcart_product_finder/locale/ru/LC_MESSAGES/django.po
pcart_product_finder/locale/uk/LC_MESSAGES/django.mo
pcart_product_finder/locale/uk/LC_MESSAGES/django.po
pcart_product_finder/migrations/0001_initial.py
pcart_product_finder/migrations/0002_auto_20171017_1442.py
pcart_product_finder/migrations/0003_auto_20171018_1432.py
pcart_product_finder/migrations/0004_auto_20171018_1543.py
pcart_product_finder/migrations/0005_auto_20171027_1133.py
pcart_product_finder/migrations/0006_auto_20171027_1651.py
pcart_product_finder/migrations/0007_auto_20171101_1426.py
pcart_product_finder/migrations/0008_auto_20171101_1427.py
pcart_product_finder/migrations/0009_auto_20171101_1427.py
pcart_product_finder/migrations/0010_auto_20171101_1447.py
pcart_product_finder/migrations/0011_auto_20171114_1502.py
pcart_product_finder/migrations/0012_productfinderformpluginmodel.py
pcart_product_finder/migrations/0013_productfinderformpluginmodel_title.py
pcart_product_finder/migrations/__init__.py
pcart_product_finder/templates/productfinder/plugins/form_plugin.html